SplitStrains/__init__.py
SplitStrains/splitStrains.py
SplitStrains-0.2.1.dist-info/METADATA
SplitStrains-0.2.1.dist-info/WHEEL
SplitStrains-0.2.1.dist-info/entry_points.txt
SplitStrains-0.2.1.dist-info/top_level.txt
SplitStrains-0.2.1.dist-info/RECORD
