Metadata-Version: 2.1
Name: SplitStrains
Version: 0.2.1
Summary: SplitStrains detects and separates mixed strains of Mycobacterium tuberculosis.
Home-page: https://github.com/WGS-TB/SplitStrains
Author: Einar Gabbasov
Author-email: 
License: UNKNOWN
Platform: UNKNOWN
Requires-Dist: matplotlib (>=3.3)
Requires-Dist: mixem
Requires-Dist: numpy (>=1.15)
Requires-Dist: pysam
Requires-Dist: scikit-learn
Requires-Dist: scipy (>=1.0)
Requires-Dist: seaborn
